singul/__init__.py
singul/assets.py
singul/base.py
singul/cases.py
singul/communication.py
singul/eradication.py
singul/iam.py
singul/intel.py
singul/module.py
singul/network.py
singul/other.py
singul/siem.py
singul/standalone.py
singul/test_module.py
singul-0.1.8.dist-info/METADATA
singul-0.1.8.dist-info/WHEEL
singul-0.1.8.dist-info/top_level.txt
singul-0.1.8.dist-info/RECORD
