Metadata-Version: 2.4
Name: singul
Version: 0.1.8
Summary: Connect to your favorite services with a singul line of code. Now runable locally.
Home-page: https://github.com/shuffle/singul
Author: Fredrik Saito Odegaardstuen
Author-email: frikky@shuffler.io
Classifier: Programming Language :: Python :: 3
Classifier: License :: OSI Approved :: MIT License
Classifier: Operating System :: OS Independent
Requires-Python: >=3.6
Requires-Dist: requests
Requires-Dist: tqdm
Dynamic: author
Dynamic: author-email
Dynamic: classifier
Dynamic: description
Dynamic: description-content-type
Dynamic: home-page
Dynamic: requires-dist
Dynamic: requires-python
Dynamic: summary
